CHANGES.rst
MANIFEST.in
README.rst
setup.py
EditOnline/EditOnline
EditOnline/EditOnline.bat
EditOnline/EditOnline.py
EditOnline/EditOnline.pyc
EditOnline/__init__.py
EditOnline/__init__.pyc
EditOnline/__main__.py
EditOnline/editor.html
EditOnline/wsgi.py
EditOnline/wsgi.pyc
EditOnline.egg-info/PKG-INFO
EditOnline.egg-info/SOURCES.txt
EditOnline.egg-info/dependency_links.txt
EditOnline.egg-info/not-zip-safe
EditOnline.egg-info/top_level.txt
EditOnline/static/ace.js
EditOnline/static/config.js
EditOnline/static/ext-beautify.js
EditOnline/static/ext-chromevox.js
EditOnline/static/ext-elastic_tabstops_lite.js
EditOnline/static/ext-emmet.js
EditOnline/static/ext-error_marker.js
EditOnline/static/ext-keybinding_menu.js
EditOnline/static/ext-language_tools.js
EditOnline/static/ext-linking.js
EditOnline/static/ext-modelist.js
EditOnline/static/ext-old_ie.js
EditOnline/static/ext-searchbox.js
EditOnline/static/ext-settings_menu.js
EditOnline/static/ext-spellcheck.js
EditOnline/static/ext-split.js
EditOnline/static/ext-static_highlight.js
EditOnline/static/ext-statusbar.js
EditOnline/static/ext-textarea.js
EditOnline/static/ext-themelist.js
EditOnline/static/ext-whitespace.js
EditOnline/static/jquery-v1.11.1.min.js
EditOnline/static/keybinding-emacs.js
EditOnline/static/keybinding-vim.js
EditOnline/static/mode-abap.js
EditOnline/static/mode-abc.js
EditOnline/static/mode-actionscript.js
EditOnline/static/mode-ada.js
EditOnline/static/mode-apache_conf.js
EditOnline/static/mode-applescript.js
EditOnline/static/mode-asciidoc.js
EditOnline/static/mode-assembly_x86.js
EditOnline/static/mode-autohotkey.js
EditOnline/static/mode-batchfile.js
EditOnline/static/mode-c9search.js
EditOnline/static/mode-c_cpp.js
EditOnline/static/mode-cirru.js
EditOnline/static/mode-clojure.js
EditOnline/static/mode-cobol.js
EditOnline/static/mode-coffee.js
EditOnline/static/mode-coldfusion.js
EditOnline/static/mode-csharp.js
EditOnline/static/mode-css.js
EditOnline/static/mode-curly.js
EditOnline/static/mode-d.js
EditOnline/static/mode-dart.js
EditOnline/static/mode-diff.js
EditOnline/static/mode-django.js
EditOnline/static/mode-dockerfile.js
