Metadata-Version: 1.1
Name: EditOnline
Version: 0.1.14
Summary: A simple online file editor by Python base on Ace.js.
Home-page: https://github.com/sintrb/EditOnline
Author: sintrb
Author-email: sintrb@gmail.com
License: Apache
Keywords: EditOnline Ace.js
Platform: UNKNOWN
Classifier: Intended Audience :: Developers
Classifier: Operating System :: OS Independent
Classifier: Programming Language :: Python :: 2.7
Classifier: Topic :: Text Editors
